{"title":"NubileFilms - Kacy Lane - october 2014","uid":11163737,"size":344624003,"categoryP":"porn","categoryS":"movies","magnet":"?xt=urn:btih:01b4cf365ba0d2c5c4c56d820d6ae17eb92b595b&amp;dn=NubileFilms+-+Kacy+Lane+-+october+2014&amp;tr=udp%3A%2F%2Ftracker.openbittorrent.com%3A80&amp;tr=udp%3A%2F%2Fopen.demonii.com%3A1337&amp;tr=udp%3A%2F%2Ftracker.coppersurfer.tk%3A6969&amp;tr=udp%3A%2F%2Fexodus.desync.com%3A6969","seeders":0,"leechers":1,"uploader":"newupload","files":1,"time":1412601992,"description":"screens ----\n\n &lt;a href=&quot;\nhttp://xxx1.imagepool.in/share-EA04_543277B9.html&quot; rel=&quot;nofollow&quot; target=&quot;_NEW&quot;&gt;\nhttp://xxx1.imagepool.in/share-EA04_543277B9.html&lt;/a&gt;\n\n &lt;a href=&quot;\nhttp://xxx1.imagepool.in/share-8497_54327C3B.html&quot; rel=&quot;nofollow&quot; target=&quot;_NEW&quot;&gt;\nhttp://xxx1.imagepool.in/share-8497_54327C3B.html&lt;/a&gt;","torrent":{"xt":"urn:btih:01b4cf365ba0d2c5c4c56d820d6ae17eb92b595b","amp;dn":"NubileFilms+-+Kacy+Lane+-+october+2014","amp;tr":["udp%3A%2F%2Ftracker.openbittorrent.com%3A80","udp%3A%2F%2Fopen.demonii.com%3A1337","udp%3A%2F%2Ftracker.coppersurfer.tk%3A6969","udp%3A%2F%2Fexodus.desync.com%3A6969"],"infoHash":"01b4cf365ba0d2c5c4c56d820d6ae17eb92b595b","infoHashBuffer":{"type":"Buffer","data":[1,180,207,54,91,160,210,197,196,197,109,130,13,106,225,126,185,43,89,91]},"announce":[],"urlList":[]}}