{"title":"Pure MILF 7","uid":11250847,"size":756889175,"categoryP":"porn","categoryS":"movies","magnet":"?xt=urn:btih:0df008b1f0a84316d561b2cc8dd0f24dcb928f87&amp;dn=Pure+MILF+7&amp;tr=udp%3A%2F%2Ftracker.openbittorrent.com%3A80&amp;tr=udp%3A%2F%2Fopen.demonii.com%3A1337&amp;tr=udp%3A%2F%2Ftracker.coppersurfer.tk%3A6969&amp;tr=udp%3A%2F%2Fexodus.desync.com%3A6969","seeders":0,"leechers":3,"uploader":"digital_ripper","files":1,"time":1413827278,"description":"screens\n &lt;a href=&quot;\nhttp://www.mypornimage.com/adultimage/A2e&quot; rel=&quot;nofollow&quot; target=&quot;_NEW&quot;&gt;\nhttp://www.mypornimage.com/adultimage/A2e&lt;/a&gt; &lt;a href=&quot;\nhttp://www.mypornimage.com/adultimage/A2o&quot; rel=&quot;nofollow&quot; target=&quot;_NEW&quot;&gt;\nhttp://www.mypornimage.com/adultimage/A2o&lt;/a&gt;\n\n\n\n\n~~~~~~~~~~~~~~~~~~~~~~~~~~~~~~~~~~~~~~~~~~~~~~~~~~~~~~~~~~~~~~~~~~~~~~~~~~~~~~~\n\n                       ````````````````````````````````\n      Downloads your favourite porn movies only from digital_ripper accounts\n~~~~~~~~~~~~~~~~~~~~~~~~~~~~~~~~~~~~~~~~~~~~~~~~~~~~~~~~~~~~~~~~~~~~~~~~~~~~~~~","torrent":{"xt":"urn:btih:0df008b1f0a84316d561b2cc8dd0f24dcb928f87","amp;dn":"Pure+MILF+7","amp;tr":["udp%3A%2F%2Ftracker.openbittorrent.com%3A80","udp%3A%2F%2Fopen.demonii.com%3A1337","udp%3A%2F%2Ftracker.coppersurfer.tk%3A6969","udp%3A%2F%2Fexodus.desync.com%3A6969"],"infoHash":"0df008b1f0a84316d561b2cc8dd0f24dcb928f87","infoHashBuffer":{"type":"Buffer","data":[13,240,8,177,240,168,67,22,213,97,178,204,141,208,242,77,203,146,143,135]},"announce":[],"urlList":[]}}