{"title":"EPL.2014.Day11.(08 nov).Burnley.v.Hull.City.720p","uid":11410596,"size":4152566481,"categoryP":"video","categoryS":"hd___tv_shows","magnet":"?xt=urn:btih:295ad7d7a15c3a94c83d42109604b485824b6451&amp;dn=EPL.2014.Day11.%2808+nov%29.Burnley.v.Hull.City.720p&amp;tr=udp%3A%2F%2Ftracker.openbittorrent.com%3A80&amp;tr=udp%3A%2F%2Fopen.demonii.com%3A1337&amp;tr=udp%3A%2F%2Ftracker.coppersurfer.tk%3A6969&amp;tr=udp%3A%2F%2Fexodus.desync.com%3A6969","seeders":0,"leechers":1,"uploader":"Nepotu","files":1,"time":1415527923,"description":"Credit: Reborn4HD","torrent":{"xt":"urn:btih:295ad7d7a15c3a94c83d42109604b485824b6451","amp;dn":"EPL.2014.Day11.%2808+nov%29.Burnley.v.Hull.City.720p","amp;tr":["udp%3A%2F%2Ftracker.openbittorrent.com%3A80","udp%3A%2F%2Fopen.demonii.com%3A1337","udp%3A%2F%2Ftracker.coppersurfer.tk%3A6969","udp%3A%2F%2Fexodus.desync.com%3A6969"],"infoHash":"295ad7d7a15c3a94c83d42109604b485824b6451","infoHashBuffer":{"type":"Buffer","data":[41,90,215,215,161,92,58,148,200,61,66,16,150,4,180,133,130,75,100,81]},"announce":[],"urlList":[]}}