{"title":"SexArt.14.10.14.Breann.Altazo.XXX.IMAGESET-GAGBALL","uid":11211456,"size":215738253,"categoryP":"porn","categoryS":"other","magnet":"?xt=urn:btih:3158be3d3b72eee30ee8b101ed8d51f35396e452&amp;dn=SexArt.14.10.14.Breann.Altazo.XXX.IMAGESET-GAGBALL&amp;tr=udp%3A%2F%2Ftracker.openbittorrent.com%3A80&amp;tr=udp%3A%2F%2Fopen.demonii.com%3A1337&amp;tr=udp%3A%2F%2Ftracker.coppersurfer.tk%3A6969&amp;tr=udp%3A%2F%2Fexodus.desync.com%3A6969","seeders":0,"leechers":1,"uploader":"DrarbgXXX","files":127,"time":1413283145,"description":" &lt;a href=&quot;https://rarbg.com&quot; rel=&quot;nofollow&quot; target=&quot;_NEW&quot;&gt;https://rarbg.com&lt;/a&gt;\n\nSexArt.com_14.10.14.Breann.Altazo.XXX.IMAGESET-GAGBALL","torrent":{"xt":"urn:btih:3158be3d3b72eee30ee8b101ed8d51f35396e452","amp;dn":"SexArt.14.10.14.Breann.Altazo.XXX.IMAGESET-GAGBALL","amp;tr":["udp%3A%2F%2Ftracker.openbittorrent.com%3A80","udp%3A%2F%2Fopen.demonii.com%3A1337","udp%3A%2F%2Ftracker.coppersurfer.tk%3A6969","udp%3A%2F%2Fexodus.desync.com%3A6969"],"infoHash":"3158be3d3b72eee30ee8b101ed8d51f35396e452","infoHashBuffer":{"type":"Buffer","data":[49,88,190,61,59,114,238,227,14,232,177,1,237,141,81,243,83,150,228,82]},"announce":[],"urlList":[]}}