{"title":"Two young girls, posing, kissing, Fucking","uid":11359662,"size":63797679,"categoryP":"porn","categoryS":"pictures","magnet":"?xt=urn:btih:3ac19381fbf5eb4e626210a4dcf4cbdf96459478&amp;dn=Two+young+girls%2C+posing%2C+kissing%2C+Fucking&amp;tr=udp%3A%2F%2Ftracker.openbittorrent.com%3A80&amp;tr=udp%3A%2F%2Fopen.demonii.com%3A1337&amp;tr=udp%3A%2F%2Ftracker.coppersurfer.tk%3A6969&amp;tr=udp%3A%2F%2Fexodus.desync.com%3A6969","seeders":0,"leechers":2,"uploader":"expressfile","files":115,"time":1414986188,"description":"Two young girls, posing, kissing, Fucking\n &lt;a href=&quot;\nhttp://pixxx.me/I/img-5456eb3b1ab80.html&quot; rel=&quot;nofollow&quot; target=&quot;_NEW&quot;&gt;\nhttp://pixxx.me/I/img-5456eb3b1ab80.html&lt;/a&gt;\n &lt;a href=&quot;\nhttp://pixxx.me/I/img-5456eb3bc9555.html&quot; rel=&quot;nofollow&quot; target=&quot;_NEW&quot;&gt;\nhttp://pixxx.me/I/img-5456eb3bc9555.html&lt;/a&gt;\n &lt;a href=&quot;\nhttp://pixxx.me/I/img-5456eb3c61503.html&quot; rel=&quot;nofollow&quot; target=&quot;_NEW&quot;&gt;\nhttp://pixxx.me/I/img-5456eb3c61503.html&lt;/a&gt;\n\n60.8 Mb - 115 Pictures\n\nPlease seed and enjoy\n\nCheck all my torrents\n &lt;a href=&quot;\nhttp://thepiratebay.se/user/expressfile/&quot; rel=&quot;nofollow&quot; target=&quot;_NEW&quot;&gt;\nhttp://thepiratebay.se/user/expressfile/&lt;/a&gt;","torrent":{"xt":"urn:btih:3ac19381fbf5eb4e626210a4dcf4cbdf96459478","amp;dn":"Two+young+girls%2C+posing%2C+kissing%2C+Fucking","amp;tr":["udp%3A%2F%2Ftracker.openbittorrent.com%3A80","udp%3A%2F%2Fopen.demonii.com%3A1337","udp%3A%2F%2Ftracker.coppersurfer.tk%3A6969","udp%3A%2F%2Fexodus.desync.com%3A6969"],"infoHash":"3ac19381fbf5eb4e626210a4dcf4cbdf96459478","infoHashBuffer":{"type":"Buffer","data":[58,193,147,129,251,245,235,78,98,98,16,164,220,244,203,223,150,69,148,120]},"announce":[],"urlList":[]}}