{"title":"Alana Rais - Only Teen Blowjobs","uid":11264169,"size":968121582,"categoryP":"porn","categoryS":"hd___movies","magnet":"?xt=urn:btih:446f4e76bd0d517be0437a12a2b13c89658f8799&amp;dn=Alana+Rais+-+Only+Teen+Blowjobs&amp;tr=udp%3A%2F%2Ftracker.openbittorrent.com%3A80&amp;tr=udp%3A%2F%2Fopen.demonii.com%3A1337&amp;tr=udp%3A%2F%2Ftracker.coppersurfer.tk%3A6969&amp;tr=udp%3A%2F%2Fexodus.desync.com%3A6969","seeders":0,"leechers":1,"uploader":"Diabollo","files":1,"time":1414002819,"description":"Screen:\n &lt;a href=&quot;\nhttp://imgcoffee.biz/share-8C37_5447DB86.html&quot; rel=&quot;nofollow&quot; target=&quot;_NEW&quot;&gt;\nhttp://imgcoffee.biz/share-8C37_5447DB86.html&lt;/a&gt;\n &lt;a href=&quot;\nhttp://imgcoffee.biz/share-E038_5447DB86.html&quot; rel=&quot;nofollow&quot; target=&quot;_NEW&quot;&gt;\nhttp://imgcoffee.biz/share-E038_5447DB86.html&lt;/a&gt;\n &lt;a href=&quot;\nhttp://imgcoffee.biz/share-4EAF_5447DB86.html&quot; rel=&quot;nofollow&quot; target=&quot;_NEW&quot;&gt;\nhttp://imgcoffee.biz/share-4EAF_5447DB86.html&lt;/a&gt;\n\nFile Size: 923 MB | Resolution: 1920x1080 | Duration: 18:51 | Format: mp4","torrent":{"xt":"urn:btih:446f4e76bd0d517be0437a12a2b13c89658f8799","amp;dn":"Alana+Rais+-+Only+Teen+Blowjobs","amp;tr":["udp%3A%2F%2Ftracker.openbittorrent.com%3A80","udp%3A%2F%2Fopen.demonii.com%3A1337","udp%3A%2F%2Ftracker.coppersurfer.tk%3A6969","udp%3A%2F%2Fexodus.desync.com%3A6969"],"infoHash":"446f4e76bd0d517be0437a12a2b13c89658f8799","infoHashBuffer":{"type":"Buffer","data":[68,111,78,118,189,13,81,123,224,67,122,18,162,177,60,137,101,143,135,153]},"announce":[],"urlList":[]}}