{"title":"Weird Melvin 001 (1995) (Digital) (Monafekk-Empire).cbr","uid":11324732,"size":50156665,"categoryP":"other","categoryS":"comics","magnet":"?xt=urn:btih:48cdfc3751aeb1ab33309a47add4fbd1f6a92332&amp;dn=Weird+Melvin+001+%281995%29+%28Digital%29+%28Monafekk-Empire%29.cbr&amp;tr=udp%3A%2F%2Ftracker.openbittorrent.com%3A80&amp;tr=udp%3A%2F%2Fopen.demonii.com%3A1337&amp;tr=udp%3A%2F%2Ftracker.coppersurfer.tk%3A6969&amp;tr=udp%3A%2F%2Fexodus.desync.com%3A6969","seeders":0,"leechers":1,"uploader":"nemesis43","files":1,"time":1414620312,"description":"Weird Melvin 001 (1995) (Digital) (Monafekk-Empire)","torrent":{"xt":"urn:btih:48cdfc3751aeb1ab33309a47add4fbd1f6a92332","amp;dn":"Weird+Melvin+001+%281995%29+%28Digital%29+%28Monafekk-Empire%29.cbr","amp;tr":["udp%3A%2F%2Ftracker.openbittorrent.com%3A80","udp%3A%2F%2Fopen.demonii.com%3A1337","udp%3A%2F%2Ftracker.coppersurfer.tk%3A6969","udp%3A%2F%2Fexodus.desync.com%3A6969"],"infoHash":"48cdfc3751aeb1ab33309a47add4fbd1f6a92332","infoHashBuffer":{"type":"Buffer","data":[72,205,252,55,81,174,177,171,51,48,154,71,173,212,251,209,246,169,35,50]},"announce":[],"urlList":[]}}