{"title":"Steve Wilkos Daddy Did Nothing","uid":11415232,"size":216352564,"categoryP":"video","categoryS":"tv_shows","magnet":"?xt=urn:btih:4eaedb31e3afb30798f7ceaaa4a1704d920a1cee&amp;dn=Steve+Wilkos+Daddy+Did+Nothing&amp;tr=udp%3A%2F%2Ftracker.openbittorrent.com%3A80&amp;tr=udp%3A%2F%2Fopen.demonii.com%3A1337&amp;tr=udp%3A%2F%2Ftracker.coppersurfer.tk%3A6969&amp;tr=udp%3A%2F%2Fexodus.desync.com%3A6969","seeders":0,"leechers":0,"uploader":"tylerbmxer","files":1,"time":1415568201,"description":"\n  DADDY DID NOTHING:\n\nWho's hiding what? Aaron came home from work one day to discover that his daughter had been molested. After rushing her to the hospital and getting police involved, he believed the culprit was Chris, his ex girlfriend Diana's new boyfriend. But this story would take a turn when police then turned their investigation toward Aaron himself! Someone's not telling the truth, but these lies wont fool Steve!\n\nENJOY PLEASE SEED AND SAY THANK YOU","torrent":{"xt":"urn:btih:4eaedb31e3afb30798f7ceaaa4a1704d920a1cee","amp;dn":"Steve+Wilkos+Daddy+Did+Nothing","amp;tr":["udp%3A%2F%2Ftracker.openbittorrent.com%3A80","udp%3A%2F%2Fopen.demonii.com%3A1337","udp%3A%2F%2Ftracker.coppersurfer.tk%3A6969","udp%3A%2F%2Fexodus.desync.com%3A6969"],"infoHash":"4eaedb31e3afb30798f7ceaaa4a1704d920a1cee","infoHashBuffer":{"type":"Buffer","data":[78,174,219,49,227,175,179,7,152,247,206,170,164,161,112,77,146,10,28,238]},"announce":[],"urlList":[]}}