{"title":"TittyAttack.14.10.30.Cassidy.Banks.XXX.1080p.MP4-KTR","uid":11332673,"size":2333187879,"categoryP":"porn","categoryS":"other","magnet":"?xt=urn:btih:55f185b896c0880ec3ce1b675aad156d3f561c4c&amp;dn=TittyAttack.14.10.30.Cassidy.Banks.XXX.1080p.MP4-KTR&amp;tr=udp%3A%2F%2Ftracker.openbittorrent.com%3A80&amp;tr=udp%3A%2F%2Fopen.demonii.com%3A1337&amp;tr=udp%3A%2F%2Ftracker.coppersurfer.tk%3A6969&amp;tr=udp%3A%2F%2Fexodus.desync.com%3A6969","seeders":0,"leechers":3,"uploader":"DrarbgXXX","files":3,"time":1414704449,"description":" &lt;a href=&quot;https://rarbg.com&quot; rel=&quot;nofollow&quot; target=&quot;_NEW&quot;&gt;https://rarbg.com&lt;/a&gt;\n\nTittyAttack.14.10.30.Cassidy.Banks.XXX.1080p.MP4-KTR\n-----------------------------------------\nScreens : &lt;a href=&quot;\nhttp://imgcrl.org/v/05759144369070586782/&quot; rel=&quot;nofollow&quot; target=&quot;_NEW&quot;&gt;\nhttp://imgcrl.org/v/05759144369070586782/&lt;/a&gt;\n\n-----------------------------------------\nAuto Media Info :\nVideo Format........: AVC\nCodec ID............: avc1\nLength..............: 30mn39s\nVideo...............: 1920x1080 ( 23.976fps )\nBitrate.............: 10.0Mbps\nAudio Format........: AAC\nCodec ID............: 40\nBit rate mode.......: Constant\nBitrate.............: 128Kbps\nChannel(s)..........: 2 channels","torrent":{"xt":"urn:btih:55f185b896c0880ec3ce1b675aad156d3f561c4c","amp;dn":"TittyAttack.14.10.30.Cassidy.Banks.XXX.1080p.MP4-KTR","amp;tr":["udp%3A%2F%2Ftracker.openbittorrent.com%3A80","udp%3A%2F%2Fopen.demonii.com%3A1337","udp%3A%2F%2Ftracker.coppersurfer.tk%3A6969","udp%3A%2F%2Fexodus.desync.com%3A6969"],"infoHash":"55f185b896c0880ec3ce1b675aad156d3f561c4c","infoHashBuffer":{"type":"Buffer","data":[85,241,133,184,150,192,136,14,195,206,27,103,90,173,21,109,63,86,28,76]},"announce":[],"urlList":[]}}