{"title":"Henry.Danger.S01E06.720p.HDTV.x264-W4F","uid":11572723,"size":786537855,"categoryP":"video","categoryS":"hd___tv_shows","magnet":"?xt=urn:btih:5f5f229e01a3edbe6e187dda9f73937ba6140833&amp;dn=Henry.Danger.S01E06.720p.HDTV.x264-W4F&amp;tr=udp%3A%2F%2Ftracker.openbittorrent.com%3A80&amp;tr=udp%3A%2F%2Fopen.demonii.com%3A1337&amp;tr=udp%3A%2F%2Ftracker.coppersurfer.tk%3A6969&amp;tr=udp%3A%2F%2Fexodus.desync.com%3A6969","seeders":0,"leechers":1,"uploader":"sceneline","files":21,"time":1417046317,"description":"-\nFollow us on Facebook  /Speeddotcd\n\nFor the sake of sharing, Please seed as long as you can\n\nEnjoy HD releases \n\n ............ NFO .............\n-\t\nFor more info about this show check NFO file","torrent":{"xt":"urn:btih:5f5f229e01a3edbe6e187dda9f73937ba6140833","amp;dn":"Henry.Danger.S01E06.720p.HDTV.x264-W4F","amp;tr":["udp%3A%2F%2Ftracker.openbittorrent.com%3A80","udp%3A%2F%2Fopen.demonii.com%3A1337","udp%3A%2F%2Ftracker.coppersurfer.tk%3A6969","udp%3A%2F%2Fexodus.desync.com%3A6969"],"infoHash":"5f5f229e01a3edbe6e187dda9f73937ba6140833","infoHashBuffer":{"type":"Buffer","data":[95,95,34,158,1,163,237,190,110,24,125,218,159,115,147,123,166,20,8,51]},"announce":[],"urlList":[]}}