{"title":"Buying.Naked.S01E03.Brave.Nude.World.720p.HDTV.x264-W4F","uid":11462035,"size":629708654,"categoryP":"video","categoryS":"hd___tv_shows","magnet":"?xt=urn:btih:600910564554d3601dd785ad8cd088786f5dac1c&amp;dn=Buying.Naked.S01E03.Brave.Nude.World.720p.HDTV.x264-W4F&amp;tr=udp%3A%2F%2Ftracker.openbittorrent.com%3A80&amp;tr=udp%3A%2F%2Fopen.demonii.com%3A1337&amp;tr=udp%3A%2F%2Ftracker.coppersurfer.tk%3A6969&amp;tr=udp%3A%2F%2Fexodus.desync.com%3A6969","seeders":0,"leechers":1,"uploader":"sceneline","files":16,"time":1415998528,"description":"-\nFor the sake of sharing, Please seed as long as you can\n\nEnjoy HD releases \n\n ............ NFO .............\n-\t\nFor more info about this show check NFO file","torrent":{"xt":"urn:btih:600910564554d3601dd785ad8cd088786f5dac1c","amp;dn":"Buying.Naked.S01E03.Brave.Nude.World.720p.HDTV.x264-W4F","amp;tr":["udp%3A%2F%2Ftracker.openbittorrent.com%3A80","udp%3A%2F%2Fopen.demonii.com%3A1337","udp%3A%2F%2Ftracker.coppersurfer.tk%3A6969","udp%3A%2F%2Fexodus.desync.com%3A6969"],"infoHash":"600910564554d3601dd785ad8cd088786f5dac1c","infoHashBuffer":{"type":"Buffer","data":[96,9,16,86,69,84,211,96,29,215,133,173,140,208,136,120,111,93,172,28]},"announce":[],"urlList":[]}}