{"title":"[MyGirlLovesAnal] Eva Long (18715 / 10.14.2014)","uid":11215683,"size":613615535,"categoryP":"porn","categoryS":"other","magnet":"?xt=urn:btih:7119683ceda4660b71300d249d675cd6e86614aa&amp;dn=%5BMyGirlLovesAnal%5D+Eva+Long+%2818715+%2F+10.14.2014%29&amp;tr=udp%3A%2F%2Ftracker.openbittorrent.com%3A80&amp;tr=udp%3A%2F%2Fopen.demonii.com%3A1337&amp;tr=udp%3A%2F%2Ftracker.coppersurfer.tk%3A6969&amp;tr=udp%3A%2F%2Fexodus.desync.com%3A6969","seeders":0,"leechers":1,"uploader":"TomcatX","files":1,"time":1413324818,"description":"[MyGirlLovesAnal] Eva Long (18715 / 10.14.2014)\n\nJohnny is ready to break up with his girlfriend, Eva Long. The sex is great, but she just nags him too much. Eva promises to give him something he has never given him before if Johnny changes his mind and stays. She offers him up her ass. Johnny decides he can put up with her for a little longer if it means he can tap that ass.\n\nScreens: &lt;a href=&quot;\nhttp://imgextra.biz/viewer.php?file=4c3xwkviwp6anojlmtjn.jpg&quot; rel=&quot;nofollow&quot; target=&quot;_NEW&quot;&gt;\nhttp://imgextra.biz/viewer.php?file=4c3xwkviwp6anojlmtjn.jpg&lt;/a&gt; &lt;a href=&quot;\nhttp://imgextra.biz/viewer.php?file=5in8uqda7tunnl8bo1n.jpg&quot; rel=&quot;nofollow&quot; target=&quot;_NEW&quot;&gt;\nhttp://imgextra.biz/viewer.php?file=5in8uqda7tunnl8bo1n.jpg&lt;/a&gt;","torrent":{"xt":"urn:btih:7119683ceda4660b71300d249d675cd6e86614aa","amp;dn":"%5BMyGirlLovesAnal%5D+Eva+Long+%2818715+%2F+10.14.2014%29","amp;tr":["udp%3A%2F%2Ftracker.openbittorrent.com%3A80","udp%3A%2F%2Fopen.demonii.com%3A1337","udp%3A%2F%2Ftracker.coppersurfer.tk%3A6969","udp%3A%2F%2Fexodus.desync.com%3A6969"],"infoHash":"7119683ceda4660b71300d249d675cd6e86614aa","infoHashBuffer":{"type":"Buffer","data":[113,25,104,60,237,164,102,11,113,48,13,36,157,103,92,214,232,102,20,170]},"announce":[],"urlList":[]}}