{"title":"[BustyBuffy] Lucie Wilde (Jacuzzi Sex Tape)","uid":11624930,"size":64706158,"categoryP":"porn","categoryS":"other","magnet":"?xt=urn:btih:73702703646619c3a8ad5f483c8cce5634adc512&amp;dn=%5BBustyBuffy%5D+Lucie+Wilde+%28Jacuzzi+Sex+Tape%29&amp;tr=udp%3A%2F%2Ftracker.openbittorrent.com%3A80&amp;tr=udp%3A%2F%2Fopen.demonii.com%3A1337&amp;tr=udp%3A%2F%2Ftracker.coppersurfer.tk%3A6969&amp;tr=udp%3A%2F%2Fexodus.desync.com%3A6969","seeders":0,"leechers":2,"uploader":"makintos13","files":1,"time":1417565785,"description":"[BustyBuffy] Lucie Wilde (Jacuzzi Sex Tape)\n\nscreens:\n &lt;a href=&quot;\nhttp://imgkool.com/img-547ef04bad42e.html&quot; rel=&quot;nofollow&quot; target=&quot;_NEW&quot;&gt;\nhttp://imgkool.com/img-547ef04bad42e.html&lt;/a&gt;","torrent":{"xt":"urn:btih:73702703646619c3a8ad5f483c8cce5634adc512","amp;dn":"%5BBustyBuffy%5D+Lucie+Wilde+%28Jacuzzi+Sex+Tape%29","amp;tr":["udp%3A%2F%2Ftracker.openbittorrent.com%3A80","udp%3A%2F%2Fopen.demonii.com%3A1337","udp%3A%2F%2Ftracker.coppersurfer.tk%3A6969","udp%3A%2F%2Fexodus.desync.com%3A6969"],"infoHash":"73702703646619c3a8ad5f483c8cce5634adc512","infoHashBuffer":{"type":"Buffer","data":[115,112,39,3,100,102,25,195,168,173,95,72,60,140,206,86,52,173,197,18]},"announce":[],"urlList":[]}}