{"title":"GHAT-061 Yabe Hisae JAV CENSORED","uid":11287371,"size":1118004383,"categoryP":"porn","categoryS":"movie_clips","magnet":"?xt=urn:btih:73d0cdad36a01df3f7a596530913b559ac9fa990&amp;dn=GHAT-061+Yabe+Hisae+JAV+CENSORED&amp;tr=udp%3A%2F%2Ftracker.openbittorrent.com%3A80&amp;tr=udp%3A%2F%2Fopen.demonii.com%3A1337&amp;tr=udp%3A%2F%2Ftracker.coppersurfer.tk%3A6969&amp;tr=udp%3A%2F%2Fexodus.desync.com%3A6969","seeders":0,"leechers":1,"uploader":"3xplanet","files":1,"time":1414290529,"description":"GHAT-061 Yabe Hisae JAV CENSORED\nCover &lt;a href=&quot;\nhttp://www.3xplanet.com/view/61632.html&quot; rel=&quot;nofollow&quot; target=&quot;_NEW&quot;&gt;\nhttp://www.3xplanet.com/view/61632.html&lt;/a&gt;\nScreenshot &lt;a href=&quot;\nhttp://www.3xplanet.com/view/61781.html&quot; rel=&quot;nofollow&quot; target=&quot;_NEW&quot;&gt;\nhttp://www.3xplanet.com/view/61781.html&lt;/a&gt;\nTitle: \nStarring: Yabe Hisae\nStudio:  STAR PARADISE\n\nTag: JAV, CENSORED, STAR PARADISE, Work alone, outdoor, Mature, exposure","torrent":{"xt":"urn:btih:73d0cdad36a01df3f7a596530913b559ac9fa990","amp;dn":"GHAT-061+Yabe+Hisae+JAV+CENSORED","amp;tr":["udp%3A%2F%2Ftracker.openbittorrent.com%3A80","udp%3A%2F%2Fopen.demonii.com%3A1337","udp%3A%2F%2Ftracker.coppersurfer.tk%3A6969","udp%3A%2F%2Fexodus.desync.com%3A6969"],"infoHash":"73d0cdad36a01df3f7a596530913b559ac9fa990","infoHashBuffer":{"type":"Buffer","data":[115,208,205,173,54,160,29,243,247,165,150,83,9,19,181,89,172,159,169,144]},"announce":[],"urlList":[]}}