{"title":"Housewife1On1.14.10.13.Monique.Alexander.XXX.2160p.MP4-KTR","uid":11202225,"size":6863353965,"categoryP":"porn","categoryS":"other","magnet":"?xt=urn:btih:75ad5fa6e96e3aecdd29aeb79581a8a6387d96b8&amp;dn=Housewife1On1.14.10.13.Monique.Alexander.XXX.2160p.MP4-KTR&amp;tr=udp%3A%2F%2Ftracker.openbittorrent.com%3A80&amp;tr=udp%3A%2F%2Fopen.demonii.com%3A1337&amp;tr=udp%3A%2F%2Ftracker.coppersurfer.tk%3A6969&amp;tr=udp%3A%2F%2Fexodus.desync.com%3A6969","seeders":0,"leechers":1,"uploader":"DrarbgXXX","files":3,"time":1413186930,"description":" &lt;a href=&quot;https://rarbg.com&quot; rel=&quot;nofollow&quot; target=&quot;_NEW&quot;&gt;https://rarbg.com&lt;/a&gt;\n\nHousewife1On1.14.10.13.Monique.Alexander.XXX.2160p.MP4-KTR\n-----------------------------------------\nScreens : &lt;a href=&quot;\nhttp://imgcrl.org/v/44922188151011719421/&quot; rel=&quot;nofollow&quot; target=&quot;_NEW&quot;&gt;\nhttp://imgcrl.org/v/44922188151011719421/&lt;/a&gt;\n\n-----------------------------------------\nAuto Media Info :\nVideo Format........: AVC\nCodec ID............: avc1\nLength..............: 36mn14s\nVideo...............: 4096x2160 ( 23.976fps )\nBitrate.............: Variable\nAudio Format........: AAC\nCodec ID............: 40\nBit rate mode.......: Constant\nBitrate.............: 317Kbps\nChannel(s)..........: 2 channels","torrent":{"xt":"urn:btih:75ad5fa6e96e3aecdd29aeb79581a8a6387d96b8","amp;dn":"Housewife1On1.14.10.13.Monique.Alexander.XXX.2160p.MP4-KTR","amp;tr":["udp%3A%2F%2Ftracker.openbittorrent.com%3A80","udp%3A%2F%2Fopen.demonii.com%3A1337","udp%3A%2F%2Ftracker.coppersurfer.tk%3A6969","udp%3A%2F%2Fexodus.desync.com%3A6969"],"infoHash":"75ad5fa6e96e3aecdd29aeb79581a8a6387d96b8","infoHashBuffer":{"type":"Buffer","data":[117,173,95,166,233,110,58,236,221,41,174,183,149,129,168,166,56,125,150,184]},"announce":[],"urlList":[]}}