{"title":"ES - Sep 17, 2015 - Jessica Creepshow and Daisy Ducati (38730).h","uid":12441081,"size":584780953,"categoryP":"porn","categoryS":"movie_clips","magnet":"?xt=urn:btih:80acdd4f08d8eb8d1b5acf6627b85b2841703934&amp;dn=ES+-+Sep+17%2C+2015+-+Jessica+Creepshow+and+Daisy+Ducati+%2838730%29.h&amp;tr=udp%3A%2F%2Ftracker.openbittorrent.com%3A80&amp;tr=udp%3A%2F%2Fopen.demonii.com%3A1337&amp;tr=udp%3A%2F%2Ftracker.coppersurfer.tk%3A6969&amp;tr=udp%3A%2F%2Fexodus.desync.com%3A6969","seeders":0,"leechers":0,"uploader":"Piratepr0n","files":1,"time":1442536018,"description":"-------------------------------------------------------------------------------------\nName:\nES - Sep 17, 2015 - Jessica Creepshow and Daisy Ducati (38730).hi.mp4\n-------------------------------------------------------------------------------------\nFile list:\nES - Sep 17, 2015 - Jessica Creepshow and Daisy Ducati (38730).hi.mp4 (558 MiB | 960x540 | 50min 53s | MPEG-4) &lt;a href=&quot;\nhttp://imgfapper.com/img-55fbe7e365294.html&quot; rel=&quot;nofollow&quot; target=&quot;_NEW&quot;&gt;\nhttp://imgfapper.com/img-55fbe7e365294.html&lt;/a&gt;","torrent":{"xt":"urn:btih:80acdd4f08d8eb8d1b5acf6627b85b2841703934","amp;dn":"ES+-+Sep+17%2C+2015+-+Jessica+Creepshow+and+Daisy+Ducati+%2838730%29.h","amp;tr":["udp%3A%2F%2Ftracker.openbittorrent.com%3A80","udp%3A%2F%2Fopen.demonii.com%3A1337","udp%3A%2F%2Ftracker.coppersurfer.tk%3A6969","udp%3A%2F%2Fexodus.desync.com%3A6969"],"infoHash":"80acdd4f08d8eb8d1b5acf6627b85b2841703934","infoHashBuffer":{"type":"Buffer","data":[128,172,221,79,8,216,235,141,27,90,207,102,39,184,91,40,65,112,57,52]},"announce":[],"urlList":[]}}