{"title":"Alpha.House.2014.720p.BRRip.XviD.AC3-RARBG","uid":11236746,"size":2882920696,"categoryP":"video","categoryS":"movies","magnet":"?xt=urn:btih:87e3a462ff226d0bc81bff14890bb2d96262810b&amp;dn=Alpha.House.2014.720p.BRRip.XviD.AC3-RARBG&amp;tr=udp%3A%2F%2Ftracker.openbittorrent.com%3A80&amp;tr=udp%3A%2F%2Fopen.demonii.com%3A1337&amp;tr=udp%3A%2F%2Ftracker.coppersurfer.tk%3A6969&amp;tr=udp%3A%2F%2Fexodus.desync.com%3A6969","seeders":0,"leechers":1,"uploader":"Drarbg","files":4,"time":1413603821,"description":" &lt;a href=&quot;https://rarbg.com&quot; rel=&quot;nofollow&quot; target=&quot;_NEW&quot;&gt;https://rarbg.com&lt;/a&gt;\n\nAlpha.House.2014.720p.BRRip.XviD.AC3-RARBG\n\nAuto IMDB: &lt;a href=&quot;\nhttp://www.imdb.com/title/tt3307774/&quot; rel=&quot;nofollow&quot; target=&quot;_NEW&quot;&gt;\nhttp://www.imdb.com/title/tt3307774/&lt;/a&gt;\n\n-----------------------------------------\nScreens : &lt;a href=&quot;\nhttp://imgcrl.org/v/68620466463630000314/&quot; rel=&quot;nofollow&quot; target=&quot;_NEW&quot;&gt;\nhttp://imgcrl.org/v/68620466463630000314/&lt;/a&gt; &lt;a href=&quot;\nhttp://imgcrl.org/v/58535962897555359581/&quot; rel=&quot;nofollow&quot; target=&quot;_NEW&quot;&gt;\nhttp://imgcrl.org/v/58535962897555359581/&lt;/a&gt; &lt;a href=&quot;\nhttp://imgcrl.org/v/53277273588686481157/&quot; rel=&quot;nofollow&quot; target=&quot;_NEW&quot;&gt;\nhttp://imgcrl.org/v/53277273588686481157/&lt;/a&gt; &lt;a href=&quot;\nhttp://imgcrl.org/v/42824531271310057203/&quot; rel=&quot;nofollow&quot; target=&quot;_NEW&quot;&gt;\nhttp://imgcrl.org/v/42824531271310057203/&lt;/a&gt; &lt;a href=&quot;\nhttp://imgcrl.org/v/95628998288923539047/&quot; rel=&quot;nofollow&quot; target=&quot;_NEW&quot;&gt;\nhttp://imgcrl.org/v/95628998288923539047/&lt;/a&gt; &lt;a href=&quot;\nhttp://imgcrl.org/v/94928845760967865625/&quot; rel=&quot;nofollow&quot; target=&quot;_NEW&quot;&gt;\nhttp://imgcrl.org/v/94928845760967865625/&lt;/a&gt; &lt;a href=&quot;\nhttp://imgcrl.org/v/40752702904895322931/&quot; rel=&quot;nofollow&quot; target=&quot;_NEW&quot;&gt;\nhttp://imgcrl.org/v/40752702904895322931/&lt;/a&gt; &lt;a href=&quot;\nhttp://imgcrl.org/v/46080579857790251679/&quot; rel=&quot;nofollow&quot; target=&quot;_NEW&quot;&gt;\nhttp://imgcrl.org/v/46080579857790251679/&lt;/a&gt; &lt;a href=&quot;\nhttp://imgcrl.org/v/62211800493246077405/&quot; rel=&quot;nofollow&quot; target=&quot;_NEW&quot;&gt;\nhttp://imgcrl.org/v/62211800493246077405/&lt;/a&gt; &lt;a href=&quot;\nhttp://imgcrl.org/v/10592274533432010929/&quot; rel=&quot;nofollow&quot; target=&quot;_NEW&quot;&gt;\nhttp://imgcrl.org/v/10592274533432010929/&lt;/a&gt; &lt;a href=&quot;\nhttp://imgcrl.org/v/26338565906482320389/&quot; rel=&quot;nofollow&quot; target=&quot;_NEW&quot;&gt;\nhttp://imgcrl.org/v/26338565906482320389/&lt;/a&gt; &lt;a href=&quot;\nhttp://imgcrl.org/v/99320260569760178276/&quot; rel=&quot;nofollow&quot; target=&quot;_NEW&quot;&gt;\nhttp://imgcrl.org/v/99320260569760178276/&lt;/a&gt;\n\n-----------------------------------------\nAuto Media Info :\nVideo Format........: MPEG-4 Visual\nCodec ID............: XVID\nCodec ID/Hint.......: XviD\nLength..............: 1h28mn\nVideo...............: 1280x720 ( 23.976fps )\nBitrate.............: 3689Kbps\nAudio Format........: AC-3\nCodec ID............: 2000\nBit rate mode.......: Constant\nBitrate.............: 640Kbps\nChannel(s)..........: 6 channels","torrent":{"xt":"urn:btih:87e3a462ff226d0bc81bff14890bb2d96262810b","amp;dn":"Alpha.House.2014.720p.BRRip.XviD.AC3-RARBG","amp;tr":["udp%3A%2F%2Ftracker.openbittorrent.com%3A80","udp%3A%2F%2Fopen.demonii.com%3A1337","udp%3A%2F%2Ftracker.coppersurfer.tk%3A6969","udp%3A%2F%2Fexodus.desync.com%3A6969"],"infoHash":"87e3a462ff226d0bc81bff14890bb2d96262810b","infoHashBuffer":{"type":"Buffer","data":[135,227,164,98,255,34,109,11,200,27,255,20,137,11,178,217,98,98,129,11]},"announce":[],"urlList":[]}}