{"title":"Sex Is All Relatives(2014)XXX DVDRip x264-XCiTE","uid":11428417,"size":1431399697,"categoryP":"porn","categoryS":"movies","magnet":"?xt=urn:btih:92913375017a409b03fabe8c005c581f118589f4&amp;dn=Sex+Is+All+Relatives%282014%29XXX+DVDRip+x264-XCiTE&amp;tr=udp%3A%2F%2Ftracker.openbittorrent.com%3A80&amp;tr=udp%3A%2F%2Fopen.demonii.com%3A1337&amp;tr=udp%3A%2F%2Ftracker.coppersurfer.tk%3A6969&amp;tr=udp%3A%2F%2Fexodus.desync.com%3A6969","seeders":0,"leechers":3,"uploader":"mrdig","files":2,"time":1415690417,"description":"\n\nSize .....  1.4 GB | Audio . AAC-LC vbr\nVideo ... 1586 kbs | CRF ........... 19\nStore ... 10.31.14 | Runtime .. 120 min\nSource ....... DVD | Format ...... x264\nCategory ... Gonzo | Resolution 720x400\n\nCAST\nCassidy Klein, Chad White, John Strong, Nikki Daniels, Sabrina Banks, Tyler Nixon, Xander Corvus, Zoey Monroe\n\nDESCRIPTION\nSex Is All Relatives: Xander is shocked to discover that the explicit sexual fantasies written in his stepdaughter`s diary, are actually about him. An illicit affair between Nikki and her stepson becomes a source of frustration when her husband`s schedule keeps interfering. Aurora`s hidden attraction for her step brother reaches a breaking point when he sets out to beat up the guys harassing her at school. After John learns that his stepdaughter`s boyfriend is turned on by father/daughter role play, he recommends that the two of them practice together first","torrent":{"xt":"urn:btih:92913375017a409b03fabe8c005c581f118589f4","amp;dn":"Sex+Is+All+Relatives%282014%29XXX+DVDRip+x264-XCiTE","amp;tr":["udp%3A%2F%2Ftracker.openbittorrent.com%3A80","udp%3A%2F%2Fopen.demonii.com%3A1337","udp%3A%2F%2Ftracker.coppersurfer.tk%3A6969","udp%3A%2F%2Fexodus.desync.com%3A6969"],"infoHash":"92913375017a409b03fabe8c005c581f118589f4","infoHashBuffer":{"type":"Buffer","data":[146,145,51,117,1,122,64,155,3,250,190,140,0,92,88,31,17,133,137,244]},"announce":[],"urlList":[]}}