{"title":"BigTitsRoundAsses - Noelle Easton ** NEW 27 november 2014 ** SD","uid":11588534,"size":420271977,"categoryP":"porn","categoryS":"other","magnet":"?xt=urn:btih:ab73e8da27d96353ea856f19274cdc6c79a2bc57&amp;dn=BigTitsRoundAsses+-+Noelle+Easton+%2A%2A+NEW+27+november+2014+%2A%2A+SD+&amp;tr=udp%3A%2F%2Ftracker.openbittorrent.com%3A80&amp;tr=udp%3A%2F%2Fopen.demonii.com%3A1337&amp;tr=udp%3A%2F%2Ftracker.coppersurfer.tk%3A6969&amp;tr=udp%3A%2F%2Fexodus.desync.com%3A6969","seeders":0,"leechers":1,"uploader":"bittuboss","files":1,"time":1417201314,"description":"27 november 2014\n\nOh man, do we got a treat for you! This babe is fucking STACKED! Perfect rack, big ol' butt and a cute face thats begging to be smashed with cock! This hottie goes by the name Noelle Easton, and she is all about getting fucked hard and sucking mean dick. Watch her get banged hard from behind as those titties bounce up and down in all out glory. Hell yeah! This nympho is the real deal man! Hardcore all out big tittie banging Bangbros style!\n\n\nScreens..\n &lt;a href=&quot;\nhttp://imgextra.biz/viewer.php?file=cg8bxeju13snpiguu6oa.jpg&quot; rel=&quot;nofollow&quot; target=&quot;_NEW&quot;&gt;\nhttp://imgextra.biz/viewer.php?file=cg8bxeju13snpiguu6oa.jpg&lt;/a&gt;\n &lt;a href=&quot;\nhttp://imgextra.biz/viewer.php?file=pox418zu9l5pjejrzysz.jpg&quot; rel=&quot;nofollow&quot; target=&quot;_NEW&quot;&gt;\nhttp://imgextra.biz/viewer.php?file=pox418zu9l5pjejrzysz.jpg&lt;/a&gt;","torrent":{"xt":"urn:btih:ab73e8da27d96353ea856f19274cdc6c79a2bc57","amp;dn":"BigTitsRoundAsses+-+Noelle+Easton+%2A%2A+NEW+27+november+2014+%2A%2A+SD+","amp;tr":["udp%3A%2F%2Ftracker.openbittorrent.com%3A80","udp%3A%2F%2Fopen.demonii.com%3A1337","udp%3A%2F%2Ftracker.coppersurfer.tk%3A6969","udp%3A%2F%2Fexodus.desync.com%3A6969"],"infoHash":"ab73e8da27d96353ea856f19274cdc6c79a2bc57","infoHashBuffer":{"type":"Buffer","data":[171,115,232,218,39,217,99,83,234,133,111,25,39,76,220,108,121,162,188,87]},"announce":[],"urlList":[]}}