{"title":"Dhurata Dora - A Bombi","uid":11571246,"size":3220951,"categoryP":"audio","categoryS":"music","magnet":"?xt=urn:btih:b2a9b57001156531d14598bb6a23893e52d7fe24&amp;dn=Dhurata+Dora+-+A+Bombi+&amp;tr=udp%3A%2F%2Ftracker.openbittorrent.com%3A80&amp;tr=udp%3A%2F%2Fopen.demonii.com%3A1337&amp;tr=udp%3A%2F%2Ftracker.coppersurfer.tk%3A6969&amp;tr=udp%3A%2F%2Fexodus.desync.com%3A6969","seeders":0,"leechers":0,"uploader":"valzonn","files":1,"time":1417027443,"description":"NEW SONG OF DHURATA","torrent":{"xt":"urn:btih:b2a9b57001156531d14598bb6a23893e52d7fe24","amp;dn":"Dhurata+Dora+-+A+Bombi+","amp;tr":["udp%3A%2F%2Ftracker.openbittorrent.com%3A80","udp%3A%2F%2Fopen.demonii.com%3A1337","udp%3A%2F%2Ftracker.coppersurfer.tk%3A6969","udp%3A%2F%2Fexodus.desync.com%3A6969"],"infoHash":"b2a9b57001156531d14598bb6a23893e52d7fe24","infoHashBuffer":{"type":"Buffer","data":[178,169,181,112,1,21,101,49,209,69,152,187,106,35,137,62,82,215,254,36]},"announce":[],"urlList":[]}}