{"title":"Diario Expansion 04.12.14","uid":11631470,"size":5836464,"categoryP":"other","categoryS":"other","magnet":"?xt=urn:btih:b3e80234cca262b823576bbbee236cf110a7fb70&amp;dn=Diario+Expansion+04.12.14&amp;tr=udp%3A%2F%2Ftracker.openbittorrent.com%3A80&amp;tr=udp%3A%2F%2Fopen.demonii.com%3A1337&amp;tr=udp%3A%2F%2Ftracker.coppersurfer.tk%3A6969&amp;tr=udp%3A%2F%2Fexodus.desync.com%3A6969","seeders":0,"leechers":1,"uploader":"virana","files":1,"time":1417678228,"description":"expansion","torrent":{"xt":"urn:btih:b3e80234cca262b823576bbbee236cf110a7fb70","amp;dn":"Diario+Expansion+04.12.14","amp;tr":["udp%3A%2F%2Ftracker.openbittorrent.com%3A80","udp%3A%2F%2Fopen.demonii.com%3A1337","udp%3A%2F%2Ftracker.coppersurfer.tk%3A6969","udp%3A%2F%2Fexodus.desync.com%3A6969"],"infoHash":"b3e80234cca262b823576bbbee236cf110a7fb70","infoHashBuffer":{"type":"Buffer","data":[179,232,2,52,204,162,98,184,35,87,107,187,238,35,108,241,16,167,251,112]},"announce":[],"urlList":[]}}