{"title":"[StrandedTeens] Farrah Flower (Redhead Road Head / 11.07.2014)","uid":11403392,"size":446530116,"categoryP":"porn","categoryS":"other","magnet":"?xt=urn:btih:bb892740329985ba233fb2ad78364ba648352702&amp;dn=%5BStrandedTeens%5D+Farrah+Flower+%28Redhead+Road+Head+%2F+11.07.2014%29&amp;tr=udp%3A%2F%2Ftracker.openbittorrent.com%3A80&amp;tr=udp%3A%2F%2Fopen.demonii.com%3A1337&amp;tr=udp%3A%2F%2Ftracker.coppersurfer.tk%3A6969&amp;tr=udp%3A%2F%2Fexodus.desync.com%3A6969","seeders":0,"leechers":1,"uploader":"TomcatX","files":1,"time":1415446663,"description":"[StrandedTeens] Farrah Flower (Redhead Road Head / 11.07.2014)\n\nWho says nice guys finish last? Sexy redhead slut Farrah Flower was so grateful this guy picked her up that she gave him a blowjob while he was driving! They pulled over and Farrah took that dick deep, rubbing her clit, and taking a big facial!\n\nScreens: &lt;a href=&quot;\nhttp://imgextra.biz/viewer.php?file=2nliaz7exm897ey0x.jpg&quot; rel=&quot;nofollow&quot; target=&quot;_NEW&quot;&gt;\nhttp://imgextra.biz/viewer.php?file=2nliaz7exm897ey0x.jpg&lt;/a&gt; &lt;a href=&quot;\nhttp://imgextra.biz/viewer.php?file=ehxnc0lzby9c4feh5sn.jpg&quot; rel=&quot;nofollow&quot; target=&quot;_NEW&quot;&gt;\nhttp://imgextra.biz/viewer.php?file=ehxnc0lzby9c4feh5sn.jpg&lt;/a&gt;","torrent":{"xt":"urn:btih:bb892740329985ba233fb2ad78364ba648352702","amp;dn":"%5BStrandedTeens%5D+Farrah+Flower+%28Redhead+Road+Head+%2F+11.07.2014%29","amp;tr":["udp%3A%2F%2Ftracker.openbittorrent.com%3A80","udp%3A%2F%2Fopen.demonii.com%3A1337","udp%3A%2F%2Ftracker.coppersurfer.tk%3A6969","udp%3A%2F%2Fexodus.desync.com%3A6969"],"infoHash":"bb892740329985ba233fb2ad78364ba648352702","infoHashBuffer":{"type":"Buffer","data":[187,137,39,64,50,153,133,186,35,63,178,173,120,54,75,166,72,53,39,2]},"announce":[],"urlList":[]}}