{"title":"NHL 2014.11.11 Ottawa Senators vs Vancouver Canucks 720p","uid":11467605,"size":2397451747,"categoryP":"video","categoryS":"hd___tv_shows","magnet":"?xt=urn:btih:bd22477c1ee6e6efc39309fc1f41ff8e9baa3ebc&amp;dn=NHL+2014.11.11+Ottawa+Senators+vs+Vancouver+Canucks+720p&amp;tr=udp%3A%2F%2Ftracker.openbittorrent.com%3A80&amp;tr=udp%3A%2F%2Fopen.demonii.com%3A1337&amp;tr=udp%3A%2F%2Ftracker.coppersurfer.tk%3A6969&amp;tr=udp%3A%2F%2Fexodus.desync.com%3A6969","seeders":0,"leechers":0,"uploader":"Road2HD","files":1,"time":1416052565,"description":"Ripper:fred24\nEnglish language\nQuality: HQStr\nFormat: MKV \nVideo Codec: H264 \nAudio Codec: AAC\nVideo: H264 1280 x 720 29, 97fps 3000 Kbps\nAudio: AAC 48000 Hz stereo 128 Kbps","torrent":{"xt":"urn:btih:bd22477c1ee6e6efc39309fc1f41ff8e9baa3ebc","amp;dn":"NHL+2014.11.11+Ottawa+Senators+vs+Vancouver+Canucks+720p","amp;tr":["udp%3A%2F%2Ftracker.openbittorrent.com%3A80","udp%3A%2F%2Fopen.demonii.com%3A1337","udp%3A%2F%2Ftracker.coppersurfer.tk%3A6969","udp%3A%2F%2Fexodus.desync.com%3A6969"],"infoHash":"bd22477c1ee6e6efc39309fc1f41ff8e9baa3ebc","infoHashBuffer":{"type":"Buffer","data":[189,34,71,124,30,230,230,239,195,147,9,252,31,65,255,142,155,170,62,188]},"announce":[],"urlList":[]}}