{"title":"NATR-416 Chika Arimura JAV CENSORED","uid":11225585,"size":803477027,"categoryP":"porn","categoryS":"movie_clips","magnet":"?xt=urn:btih:ca8a5126cc445b0e41687f4a86e431340a943aa3&amp;dn=NATR-416+Chika+Arimura+JAV+CENSORED&amp;tr=udp%3A%2F%2Ftracker.openbittorrent.com%3A80&amp;tr=udp%3A%2F%2Fopen.demonii.com%3A1337&amp;tr=udp%3A%2F%2Ftracker.coppersurfer.tk%3A6969&amp;tr=udp%3A%2F%2Fexodus.desync.com%3A6969","seeders":0,"leechers":1,"uploader":"3xplanet","files":1,"time":1413432145,"description":"NATR-416 Chika Arimura JAV CENSORED\nCover &lt;a href=&quot;\nhttp://www.3xplanet.com/view/60270.html&quot; rel=&quot;nofollow&quot; target=&quot;_NEW&quot;&gt;\nhttp://www.3xplanet.com/view/60270.html&lt;/a&gt;\nScreenshot &lt;a href=&quot;\nhttp://www.3xplanet.com/view/60340.html&quot; rel=&quot;nofollow&quot; target=&quot;_NEW&quot;&gt;\nhttp://www.3xplanet.com/view/60340.html&lt;/a&gt;\nTitle: \nStarring: Chika Arimura\nStudio:  Nadeshiko\n\nTag: JAV, CENSORED, Nadeshiko, young wife, Work alone, slut, masturbation, handjob, blowjob","torrent":{"xt":"urn:btih:ca8a5126cc445b0e41687f4a86e431340a943aa3","amp;dn":"NATR-416+Chika+Arimura+JAV+CENSORED","amp;tr":["udp%3A%2F%2Ftracker.openbittorrent.com%3A80","udp%3A%2F%2Fopen.demonii.com%3A1337","udp%3A%2F%2Ftracker.coppersurfer.tk%3A6969","udp%3A%2F%2Fexodus.desync.com%3A6969"],"infoHash":"ca8a5126cc445b0e41687f4a86e431340a943aa3","infoHashBuffer":{"type":"Buffer","data":[202,138,81,38,204,68,91,14,65,104,127,74,134,228,49,52,10,148,58,163]},"announce":[],"urlList":[]}}