{"title":"Mother Daughter Exchange Club 35(2014)XXX DVDRip x264-UPPERCUT","uid":11631772,"size":1405555884,"categoryP":"porn","categoryS":"movies","magnet":"?xt=urn:btih:d81dd0bb3394d99d237bbc556fde850114d9f2a1&amp;dn=Mother+Daughter+Exchange+Club+35%282014%29XXX+DVDRip+x264-UPPERCUT&amp;tr=udp%3A%2F%2Ftracker.openbittorrent.com%3A80&amp;tr=udp%3A%2F%2Fopen.demonii.com%3A1337&amp;tr=udp%3A%2F%2Ftracker.coppersurfer.tk%3A6969&amp;tr=udp%3A%2F%2Fexodus.desync.com%3A6969","seeders":0,"leechers":1,"uploader":"mrdig","files":2,"time":1417685010,"description":"screens with no ads\n\n\n\nRelease date: 02/12/2014            Runtime    : 185 Mins    \nStore date  : 15/10/2014            Genre      : All Girl\nProd year   : 2014                  Studio   : Girlfriends Films\nSource      : NTSC DVD\nFormat      : x264 crf-20\nSize        : 1.4 GB\nResolution  : 720x404\nRelease AR  : 1.782 16:9\nVideo avg bitrate : 891kbps\nAudio       : AAC-LC\n\nCAST\nJulia Ann, Marley Matthews, Mindi Mink, Nicole Moore, Raquel Sieb, Staci Carr, Tara Morgan\n\nDESCRIPTION\nMother Daughter Exchange Club 35: Moms and their daughters mix with other romance-minded mom-daughter pairs when they join Mother-Daughter Exchange Club!","torrent":{"xt":"urn:btih:d81dd0bb3394d99d237bbc556fde850114d9f2a1","amp;dn":"Mother+Daughter+Exchange+Club+35%282014%29XXX+DVDRip+x264-UPPERCUT","amp;tr":["udp%3A%2F%2Ftracker.openbittorrent.com%3A80","udp%3A%2F%2Fopen.demonii.com%3A1337","udp%3A%2F%2Ftracker.coppersurfer.tk%3A6969","udp%3A%2F%2Fexodus.desync.com%3A6969"],"infoHash":"d81dd0bb3394d99d237bbc556fde850114d9f2a1","infoHashBuffer":{"type":"Buffer","data":[216,29,208,187,51,148,217,157,35,123,188,85,111,222,133,1,20,217,242,161]},"announce":[],"urlList":[]}}