{"title":"[CasualTeenSex] Emma (Photos And Sex For Hot Redhead / 10.28.201","uid":11337321,"size":408884896,"categoryP":"porn","categoryS":"other","magnet":"?xt=urn:btih:e5074bb5d505454a324f56d2cedd2ed23561ccda&amp;dn=%5BCasualTeenSex%5D+Emma+%28Photos+And+Sex+For+Hot+Redhead+%2F+10.28.201&amp;tr=udp%3A%2F%2Ftracker.openbittorrent.com%3A80&amp;tr=udp%3A%2F%2Fopen.demonii.com%3A1337&amp;tr=udp%3A%2F%2Ftracker.coppersurfer.tk%3A6969&amp;tr=udp%3A%2F%2Fexodus.desync.com%3A6969","seeders":0,"leechers":1,"uploader":"TomcatX","files":1,"time":1414765496,"description":"[CasualTeenSex] Emma (Photos And Sex For Hot Redhead / 10.28.2014)\n\n&lt;&lt;&lt;:::: SCREENS ::::&gt;&gt;&gt; &lt;a href=&quot;\nhttp://imgextra.biz/viewer.php?file=pigvzf69692gpnpzcc9u.jpeg&quot; rel=&quot;nofollow&quot; target=&quot;_NEW&quot;&gt;\nhttp://imgextra.biz/viewer.php?file=pigvzf69692gpnpzcc9u.jpeg&lt;/a&gt; &lt;a href=&quot;\nhttp://imgextra.biz/viewer.php?file=6g9ps0mev2050u1jkgx.jpeg&quot; rel=&quot;nofollow&quot; target=&quot;_NEW&quot;&gt;\nhttp://imgextra.biz/viewer.php?file=6g9ps0mev2050u1jkgx.jpeg&lt;/a&gt;\n\n\n&lt;&lt;&lt;FOR MORE CLICK HERE&gt;&gt;&gt; &lt;a href=&quot;\nhttp://thepiratebay.si/user/TomcatX/&quot; rel=&quot;nofollow&quot; target=&quot;_NEW&quot;&gt;\nhttp://thepiratebay.si/user/TomcatX/&lt;/a&gt;\n\n\nNOTE : DON'T FORGET TO SEED","torrent":{"xt":"urn:btih:e5074bb5d505454a324f56d2cedd2ed23561ccda","amp;dn":"%5BCasualTeenSex%5D+Emma+%28Photos+And+Sex+For+Hot+Redhead+%2F+10.28.201","amp;tr":["udp%3A%2F%2Ftracker.openbittorrent.com%3A80","udp%3A%2F%2Fopen.demonii.com%3A1337","udp%3A%2F%2Ftracker.coppersurfer.tk%3A6969","udp%3A%2F%2Fexodus.desync.com%3A6969"],"infoHash":"e5074bb5d505454a324f56d2cedd2ed23561ccda","infoHashBuffer":{"type":"Buffer","data":[229,7,75,181,213,5,69,74,50,79,86,210,206,221,46,210,53,97,204,218]},"announce":[],"urlList":[]}}