{"title":"GVG-054 Sakuragi EmiKaori JAV CENSORED","uid":11262437,"size":1364619353,"categoryP":"porn","categoryS":"movie_clips","magnet":"?xt=urn:btih:eb243b5e00264787b338d1605e573a0caa9abca6&amp;dn=GVG-054+Sakuragi+EmiKaori+JAV+CENSORED&amp;tr=udp%3A%2F%2Ftracker.openbittorrent.com%3A80&amp;tr=udp%3A%2F%2Fopen.demonii.com%3A1337&amp;tr=udp%3A%2F%2Ftracker.coppersurfer.tk%3A6969&amp;tr=udp%3A%2F%2Fexodus.desync.com%3A6969","seeders":0,"leechers":1,"uploader":"3xplanet","files":1,"time":1413984989,"description":"GVG-054 Sakuragi EmiKaori JAV CENSORED\nCover &lt;a href=&quot;\nhttp://www.3xplanet.com/view/61008.html&quot; rel=&quot;nofollow&quot; target=&quot;_NEW&quot;&gt;\nhttp://www.3xplanet.com/view/61008.html&lt;/a&gt;\nScreenshot &lt;a href=&quot;\nhttp://www.3xplanet.com/view/61061.html&quot; rel=&quot;nofollow&quot; target=&quot;_NEW&quot;&gt;\nhttp://www.3xplanet.com/view/61061.html&lt;/a&gt;\nTitle: \nStarring: Sakuragi EmiKaori\nStudio:  Glory Quest\n\nTag: JAV, CENSORED, Glory Quest, Work alone, toy, slave, shyness, housewife, drama","torrent":{"xt":"urn:btih:eb243b5e00264787b338d1605e573a0caa9abca6","amp;dn":"GVG-054+Sakuragi+EmiKaori+JAV+CENSORED","amp;tr":["udp%3A%2F%2Ftracker.openbittorrent.com%3A80","udp%3A%2F%2Fopen.demonii.com%3A1337","udp%3A%2F%2Ftracker.coppersurfer.tk%3A6969","udp%3A%2F%2Fexodus.desync.com%3A6969"],"infoHash":"eb243b5e00264787b338d1605e573a0caa9abca6","infoHashBuffer":{"type":"Buffer","data":[235,36,59,94,0,38,71,135,179,56,209,96,94,87,58,12,170,154,188,166]},"announce":[],"urlList":[]}}