{"title":"My Friend's Hot Girl - Dee Dee Lynn","uid":11176000,"size":247636657,"categoryP":"porn","categoryS":"movie_clips","magnet":"?xt=urn:btih:ec02c8bd0953d5da36cc4035071706b628a31f52&amp;dn=My+Friend%27s+Hot+Girl+-+Dee+Dee+Lynn&amp;tr=udp%3A%2F%2Ftracker.openbittorrent.com%3A80&amp;tr=udp%3A%2F%2Fopen.demonii.com%3A1337&amp;tr=udp%3A%2F%2Ftracker.coppersurfer.tk%3A6969&amp;tr=udp%3A%2F%2Fexodus.desync.com%3A6969","seeders":0,"leechers":1,"uploader":"eliotmali","files":1,"time":1412787784,"description":" &lt;a href=&quot;\nhttp://imageon.org/img-543551fe0c8a9.html&quot; rel=&quot;nofollow&quot; target=&quot;_NEW&quot;&gt;\nhttp://imageon.org/img-543551fe0c8a9.html&lt;/a&gt; \n &lt;a href=&quot;\nhttp://imageon.org/img-543551fe39f01.html&quot; rel=&quot;nofollow&quot; target=&quot;_NEW&quot;&gt;\nhttp://imageon.org/img-543551fe39f01.html&lt;/a&gt; \n\n\n\nMy Friend's Hot Girl - Dee Dee Lynn\nAdded: October 8, 2014\n\nDee Dee Lynn just got back from the movies with her boyfriend's friend, Bill. Seems like Dee Dee and Bill have more in common than Dee Dee and her current boyfriend. Dee Dee and Bill quickly realize this and decide to take the plunge by having Bill plunge his giant dick inside of Dee Dee's vagina.","torrent":{"xt":"urn:btih:ec02c8bd0953d5da36cc4035071706b628a31f52","amp;dn":"My+Friend%27s+Hot+Girl+-+Dee+Dee+Lynn","amp;tr":["udp%3A%2F%2Ftracker.openbittorrent.com%3A80","udp%3A%2F%2Fopen.demonii.com%3A1337","udp%3A%2F%2Ftracker.coppersurfer.tk%3A6969","udp%3A%2F%2Fexodus.desync.com%3A6969"],"infoHash":"ec02c8bd0953d5da36cc4035071706b628a31f52","infoHashBuffer":{"type":"Buffer","data":[236,2,200,189,9,83,213,218,54,204,64,53,7,23,6,182,40,163,31,82]},"announce":[],"urlList":[]}}